README
hgspellcheck.py
setup.py
hgspellcheck.egg-info/PKG-INFO
hgspellcheck.egg-info/SOURCES.txt
hgspellcheck.egg-info/dependency_links.txt
hgspellcheck.egg-info/requires.txt
hgspellcheck.egg-info/top_level.txt
hgspellcheck.egg-info/zip-safe