Metadata-Version: 1.0
Name: hgspellcheck
Version: 1.0rc2
Summary: Hook and extension to spellcheck Mercurial commit messages
Home-page: http://bitbucket.org/ilowe/hgspellcheck
Author: Iain Lowe
Author-email: me@ilowe.net
License: MIT
Download-URL: http://bitbucket.org/ilowe/hgspellcheck/downloads
Keywords: mercurial hg scm spelling spellcheck spellchecker
Platform: UNKNOWN
